README.md
setup.py
dss_p_s/__init__.py
dss_p_s/db_utils.py
dss_p_s/dss_utils.py
dss_p_s/http_utils.py
dss_p_s/memory_utils.py
dss_p_s/misc_utils.py
dss_p_s/queue_utils.py
dss_p_s/test_db_utils.py
dss_p_s/test_memory_utils.py
dss_p_s/test_misc_utils.py
dss_p_s/test_queue_utils.py
dss_p_s.egg-info/PKG-INFO
dss_p_s.egg-info/SOURCES.txt
dss_p_s.egg-info/dependency_links.txt
dss_p_s.egg-info/requires.txt
dss_p_s.egg-info/top_level.txt