Metadata-Version: 2.1
Name: dss-p-s
Version: 0.10.0
Summary: data source management system  python sdk
Home-page: 
Author: popzh2004
Author-email: 
